kivmob.py
setup.py
kivmob.egg-info/PKG-INFO
kivmob.egg-info/SOURCES.txt
kivmob.egg-info/dependency_links.txt
kivmob.egg-info/not-zip-safe
kivmob.egg-info/requires.txt
kivmob.egg-info/top_level.txt