Metadata-Version: 1.0
Name: kivmob
Version: 1.1
Summary: Provides AdMob support for Kivy.
Home-page: http://github.com/MichaelStott/KivMob
Author: Michael Stott
Author-email: UNKNOWN
License: MIT
Platform: UNKNOWN
